aioredisorm/__init__.py
aioredisorm/aioredisorm.py
aioredisorm-0.1.3.dist-info/LICENSE
aioredisorm-0.1.3.dist-info/WHEEL
aioredisorm-0.1.3.dist-info/METADATA
aioredisorm-0.1.3.dist-info/RECORD
