Metadata-Version: 2.1
Name: aioredisorm
Version: 0.1.3
Summary: A Python class for interacting with Redis using asyncio and aioredis.
Author: fadedreams7
Author-email: fadedreams7@gmail.com
Requires-Python: >=3.8,<4.0
Classifier: Programming Language :: Python :: 3
Classifier: Programming Language :: Python :: 3.10
Classifier: Programming Language :: Python :: 3.8
Classifier: Programming Language :: Python :: 3.9
Requires-Dist: aioredis (>=2.0.1,<3.0.0)
Requires-Dist: asyncio (>=3.4.3,<4.0.0)
Project-URL: repository, https://github.com/fadedreams/aioredisorm
